avocado_result_html/__init__.py
avocado_result_html/templates/avocado_html.js
avocado_result_html/templates/bootstrap.css
avocado_result_html/templates/bootstrap.js
avocado_result_html/templates/bootstrap.min.css
avocado_result_html/templates/bootstrap.min.js
avocado_result_html/templates/datatables.css
avocado_result_html/templates/datatables.js
avocado_result_html/templates/datatables.min.js
avocado_result_html/templates/jquery.js
avocado_result_html/templates/jquery.min.js
avocado_result_html/templates/results.html
avocado_result_html/templates/style.css
avocado_result_html/templates/images/logs_icon.svg
avocado_result_html/templates/images/whiteboard_icon.svg
tests/__init__.py
tests/html_result.py
avocado_framework_plugin_result_html-113.0.dist-info/METADATA
avocado_framework_plugin_result_html-113.0.dist-info/WHEEL
avocado_framework_plugin_result_html-113.0.dist-info/entry_points.txt
avocado_framework_plugin_result_html-113.0.dist-info/top_level.txt
avocado_framework_plugin_result_html-113.0.dist-info/RECORD
