Metadata-Version: 2.4
Name: avocado-framework-plugin-result-html
Version: 113.0
Summary: Avocado HTML Report for Jobs
Home-page: http://avocado-framework.github.io/
Author: Avocado Developers
Author-email: avocado-devel@redhat.com
Requires-Dist: avocado-framework==113.0
Requires-Dist: jinja2
Requires-Dist: markupsafe<3.0.0
Dynamic: author
Dynamic: author-email
Dynamic: description
Dynamic: description-content-type
Dynamic: home-page
Dynamic: requires-dist
Dynamic: summary
